FrustrationDynamiX/__init__.py
FrustrationDynamiX/core.py
FrustrationDynamiX-0.3.2.dist-info/LICENSE
FrustrationDynamiX-0.3.2.dist-info/METADATA
FrustrationDynamiX-0.3.2.dist-info/WHEEL
FrustrationDynamiX-0.3.2.dist-info/top_level.txt
FrustrationDynamiX-0.3.2.dist-info/RECORD
