Metadata-Version: 2.1
Name: FrustrationDynamiX
Version: 0.3.2
Summary: A package for handling computing frustration in dynamical systems
Home-page: https://github.com/asb24repo/FrustrationDynamiX
Author: Ali S. Badereddine
Author-email: asb24@mail.aub.edu
License: MIT
Classifier: Development Status :: 3 - Alpha
Classifier: Intended Audience :: Science/Research
Classifier: License :: OSI Approved :: MIT License
Classifier: Programming Language :: Python :: 3
Classifier: Programming Language :: Python :: 3.6
Classifier: Programming Language :: Python :: 3.7
Classifier: Programming Language :: Python :: 3.8
Classifier: Programming Language :: Python :: 3.9
Requires-Python: >=3.6
License-File: LICENSE
Requires-Dist: numpy
Requires-Dist: pandas
Requires-Dist: matplotlib
Requires-Dist: networkx
Requires-Dist: scipy
Requires-Dist: ortools
Requires-Dist: tqdm
Requires-Dist: pyEDM ==1.14.3
